PRESENT/Evaluation.py
PRESENT/Layers.py
PRESENT/Main.py
PRESENT/Model.py
PRESENT/Utils.py
PRESENT/__init__.py
bio_present-1.0.2.dist-info/LICENSE
bio_present-1.0.2.dist-info/METADATA
bio_present-1.0.2.dist-info/WHEEL
bio_present-1.0.2.dist-info/top_level.txt
bio_present-1.0.2.dist-info/RECORD
