Metadata-Version: 2.1
Name: bio-present
Version: 1.0.2
Summary: Cross-modality representation and multi-sample integration of spatially resolved omics data
Home-page: https://github.com/lizhen18THU/PRESENT
Author: Zhen Li
Author-email: lizhen18@tsinghua.org.cn
License: MIT License
Keywords: pip,present,spatial omics
Platform: UNKNOWN
Classifier: Intended Audience :: Science/Research
Classifier: License :: OSI Approved :: MIT License
Classifier: Programming Language :: Python :: 3.8
Classifier: Operating System :: MacOS :: MacOS X
Classifier: Operating System :: Microsoft :: Windows
Classifier: Operating System :: POSIX :: Linux
Classifier: Topic :: Scientific/Engineering :: Bio-Informatics
Requires-Python: >3.6.0
License-File: LICENSE
Requires-Dist: numpy (==1.24.4)
Requires-Dist: pandas (==2.0.3)
Requires-Dist: louvain (==0.8.0)
Requires-Dist: leidenalg (==0.9.1)
Requires-Dist: scipy (==1.9.3)
Requires-Dist: scikit-learn (==1.3.2)
Requires-Dist: anndata (==0.9.2)
Requires-Dist: networkx (==3.1)
Requires-Dist: scanpy (==1.9.8)
Requires-Dist: episcanpy (==0.3.2)
Requires-Dist: genomicranges (==0.4.2)
Requires-Dist: iranges (==0.2.1)
Requires-Dist: biocutils (==0.1.3)
Requires-Dist: torch (==2.0.0)
Requires-Dist: torch-geometric (==2.3.1)
